pyveris/client.py
pyveris/constants.py
pyveris-0.1.0.dist-info/WHEEL
pyveris-0.1.0.dist-info/METADATA
pyveris-0.1.0.dist-info/RECORD
