Metadata-Version: 2.1
Name: pyveris
Version: 0.1.0
Summary: Converis API client written in python
Author: André Sartori
Author-email: sartori@ebi.ac.uk
Requires-Python: >=3.8,<4.0
Classifier: Programming Language :: Python :: 3
Classifier: Programming Language :: Python :: 3.8
Classifier: Programming Language :: Python :: 3.9
Classifier: Programming Language :: Python :: 3.10
Classifier: Programming Language :: Python :: 3.11
Requires-Dist: requests (>=2.28.1,<3.0.0)
